karka/__init__.py
karka/error.py
karka/evaluation.py
karka/input_utility.py
karka/karka.py
karka/loss_graph.py
karka/predict_graph.py
karka/rec_graph.py
karka/rep_graph.py
karka/sessions.py
karka/utility.py
Karka-0.0.3.dist-info/LICENSE
Karka-0.0.3.dist-info/LICENSE.md
Karka-0.0.3.dist-info/LICENSE.txt
Karka-0.0.3.dist-info/METADATA
Karka-0.0.3.dist-info/WHEEL
Karka-0.0.3.dist-info/top_level.txt
Karka-0.0.3.dist-info/RECORD
